{"@type":"dcat:Dataset","accessLevel":"public","bureauCode":["009:38"],"contactPoint":{"fn":"Health Data Initiative","hasEmail":"mailto:mmrr-editors@cms.hhs.gov"},"description":"<p>The Chronic Conditions PUFs are aggregated files in which each record is a profile or cell defined by the characteristics of Medicare beneficiaries. A profile is defined by all combinations of age category, gender, various chronic conditions, and dual-eligibility status of the beneficiaries.</p>\n","identifier":"476","keyword":["Chronic Condition","Interactive Tools"],"language":["en"],"license":"http://opendefinition.org/licenses/odc-odbl/","modified":"2016-08-04","programCode":["009:000"],"publisher":{"@type":"org:Organization","name":"Centers for Medicare &amp; Medicaid Services"},"temporal":"2008-01-01T00:00:00-05:00/2010-12-31T00:00:00-05:00","title":"Chronic Conditions PUF"}
