{"@type":"dcat:Dataset","accessLevel":"public","bureauCode":["009:38"],"contactPoint":{"fn":"Health Data Initiative","hasEmail":"mailto:Healthdata@hhs.gov"},"description":"<p>A set of seven (7) public use files containing information on health insurance issuers participating in the Health Insurance Marketplace and certified qualified health plans (QHPs) offered on HealthCare.gov. Plan information incudes details about essential health benefits, cost sharing, rates, and geographic coverage.</p>\n","distribution":[{"@type":"dcat:Distribution","downloadURL":"http://www.cms.gov/CCIIO/Resources/Data-Resources/marketplace-puf.html","mediaType":"application/unknown","format":"html","title":"html","identifier":"html-3a160454-4d9a-4678-a958-0a4e9bd9b5de","interra-published":true}],"identifier":"546","keyword":["Center for Consumer Information and Insurance Oversight","Covered Services","Freedom of Information Act (FOIA)","Health Insurance Marketplace","Interactive Tools","Payment Sources","Publically Available Data File - for download"],"language":["en"],"license":"http://opendefinition.org/licenses/odc-odbl/","modified":"2017-03-18","programCode":["009:000"],"publisher":{"@type":"org:Organization","name":"Centers for Medicare &amp; Medicaid Services"},"temporal":"2014-01-01T00:00:00-05:00/2016-12-31T00:00:00-05:00","title":"Health Insurance Marketplace Public Use Files"}
