{"@type":"dcat:Dataset","accessLevel":"public","bureauCode":["009:10"],"contactPoint":{"fn":"openFDA","hasEmail":"mailto:open@fda.hhs.gov"},"description":"<p>This list includes human and pet food subject to recall in the United States since January 2009 related to peanut products distributed by Peanut Corporation of America.</p>\n","distribution":[{"@type":"dcat:Distribution","downloadURL":"http://www.accessdata.fda.gov/scripts/peanutbutterrecall/PeanutButterProducts2009.xml","mediaType":"application/unknown","format":"unknown","title":"Unknown","identifier":"unknown-437879de-41ba-4ae6-8054-dc93c78500ee","interra-published":true}],"identifier":"76ceca1c-bf1a-4853-ac26-89afde382f4c","keyword":["recalls"],"language":["en"],"license":"http://opendefinition.org/licenses/odc-odbl/","modified":"2016-09-02","programCode":["009:001"],"publisher":{"@type":"org:Organization","name":"Department of Health &amp; Human Services"},"title":"Peanut Product Recalls"}
