{"@type":"dcat:Dataset","accessLevel":"public","bureauCode":["009:20"],"contactPoint":{"fn":"admin","hasEmail":"mailto:HealthData@hhs.gov"},"description":"<p>Lists the datasets for this domain.  The format should correspond to the spec at <a href=\"http://project-open-data.github.io/schema/\">http://project-open-data.github.io/schema/</a></p>\n","identifier":"7d602bed-08dd-40a4-a45e-1aef114ae648","keyword":["catalog"],"language":["en"],"license":"http://opendefinition.org/licenses/odc-odbl/","modified":"2016-04-05","publisher":{"@type":"org:Organization","name":"Department of Health &amp; Human Services"},"title":"Project Open Data, /data.json file","programCode":["009:000"]}
