{"@type":"dcat:Dataset","accessLevel":"public","bureauCode":["009:38"],"contactPoint":{"fn":"Health Data Initiative","hasEmail":"mailto:cms.data@cms.hhs.gov"},"description":"<p>The Group Unique Physician Identifier Number (UPIN) File is the business entity file that contains the group practice UPIN and descriptive information.  It does NOT associate individual physicians within the practice.</p>\n","identifier":"241","keyword":["Publically Available Data File - for purchase"],"language":["en"],"license":"http://opendefinition.org/licenses/odc-odbl/","modified":"2016-08-04","programCode":["009:000"],"publisher":{"@type":"org:Organization","name":"Centers for Medicare &amp; Medicaid Services"},"temporal":"2007-01-01T00:00:00-05:00/2008-01-01T00:00:00-05:00","title":"UPIN Group File"}
