{"@type":"dcat:Dataset","accessLevel":"public","bureauCode":["009:38"],"contactPoint":{"fn":"Health Data Initiative","hasEmail":"mailto:cms.data@cms.hhs.gov"},"description":"<p>The PERM program measures improper payments in Medicaid and CHIP and produces error rates for each program.  The error rates are based on reviews of the fee-for-service (FFS), managed care, and eligibility components of Medicaid and CHIP in the fiscal year (FY) under review.</p>\n","identifier":"243","keyword":["Medicaid Managed Care","Payment Error Rate"],"language":["en"],"license":"http://opendefinition.org/licenses/odc-odbl/","modified":"2016-08-04","programCode":["009:000"],"publisher":{"@type":"org:Organization","name":"Centers for Medicare &amp; Medicaid Services"},"title":"Payment Error Rate Measurement (PERM)"}
