{"@type":"dcat:Dataset","accessLevel":"public","bureauCode":["009:38"],"contactPoint":{"fn":"Health Data Initiative","hasEmail":"mailto:cms.data@cms.hhs.gov"},"description":"<p>PHS Act section 2719 requires non-grandfathered group health plans and health insurance issuers offering non-grandfathered health insurance coverage to provide relevant notices in a culturally and linguistically appropriate manner.  The regulations implementing section 2719 require these plans and issuers to make certain accommodations for notices sent to an address in a county meeting a threshold percentage of people who are literate only in the same non-English language.<br />\nThe list below includes all counties which meet or exceed the 10 percent threshold for the 2006-2010 ACS data and is applicable for 2012.</p>\n","identifier":"303","keyword":["Center for Consumer Information and Insurance Oversight","Fact Sheets","Minority Health"],"language":["en"],"license":"http://opendefinition.org/licenses/odc-odbl/","modified":"2016-08-04","programCode":["009:000"],"publisher":{"@type":"org:Organization","name":"Centers for Medicare &amp; Medicaid Services"},"temporal":"2012-01-01T00:00:00-05:00/2013-01-01T00:00:00-05:00","title":"Culturally and Linguistically Appropriate Services Cnty Data"}
