{"@type":"dcat:Dataset","accessLevel":"public","bureauCode":["009:38"],"contactPoint":{"fn":"admin","hasEmail":"mailto:HealthData@hhs.gov"},"description":"<p>Studies and projects - standardized methods - performance measures.</p>\n","identifier":"316eec4d-dc71-495e-8a23-5c6ebf0db332","keyword":["access-to-care","admissions","chronic-condition","disparity","end-stage-renal-disease-esrd","external-source","home-health-hha","hospice","medicaid","medicare","national","nursing-home","quality","short-stay-hospital-ssh","skilled-nursing-snf","state"],"language":["en"],"license":"http://opendefinition.org/licenses/odc-odbl/","modified":"2016-04-05","publisher":{"@type":"org:Organization","name":"Department of Health &amp; Human Services"},"title":"AHRQ - Measuring Healthcare Quality","programCode":["009:000"]}
