{"@type":"dcat:Dataset","accessLevel":"restricted public","bureauCode":["009:38"],"contactPoint":{"fn":"Health Data Initiative","hasEmail":"mailto:SharedSavingsProgram@cms.hhs.gov"},"describedBy":"http://www.resdac.org/sites/resdac.org/files/CMS%20Data%20Dictionary%20-%20SSP%20ACO%20Beneficiary-level.xlsx","description":"<p>The Centers for Medicare (CM) has created a set of standard analytical files that contain Shared Savings Program Accountable Care Organizations. Beneficiary-level research identifiable file (RIF) that will contain a record for every beneficiary that participated in the Shared Savings Program.<br />\nThe data file is structured in a way that allows CMS to respond to a wide range of potential inquiries. For example, analysts should be able to use the data to examine differences in beneficiary characteristics between ACO and non-ACO beneficiaries, stability of beneficiary alignment during and across performance years and the extent to which aligned beneficiaries receive care outside of the ACO, differences in beneficiary characteristics between ACO aligned beneficiaries who were and were not used for financial reconciliation.</p>\n","distribution":[{"@type":"dcat:Distribution","downloadURL":"http://www.resdac.org/cms-data/files/ssp-aco-beneficiary-level-rif","mediaType":"application/unknown","title":"Resource","identifier":"resource-9de57084-a7ff-4281-bd73-21b6f1d3ee02","interra-published":true}],"identifier":"575","keyword":["Accountable Care Organization"],"language":["en"],"license":"http://opendefinition.org/licenses/odc-odbl/","modified":"2016-07-22","programCode":["009:000"],"publisher":{"@type":"org:Organization","name":"Centers for Medicare &amp; Medicaid Services"},"temporal":"2016-06-23T20:13:00-04:00/2016-06-23T20:13:00-04:00","title":"Shared Savings Program ACO Beneficiary-level RIF"}
