{"@type":"dcat:Dataset","accessLevel":"public","bureauCode":["009:10"],"contactPoint":{"fn":"openFDA","hasEmail":"mailto:open@fda.hhs.gov"},"description":"<p>This database consists of those national and international standards recognized by FDA which manufacturers can declare conformity to and is part of the information the Center can use to make an appropriate decision regarding the clearance or approval of a submission. Information submitted on conformance with such standards will have a direct bearing on safety and effectiveness determinations made during the review of IDEs, HDEs, PMAs, and PDPs. Conformance with recognized consensus standards in and of itself, however, may not always be a sufficient basis for regulatory decisions.</p>\n","identifier":"75def5d4-11ce-4553-b16b-dabc271b177d","keyword":["cdrh"],"language":["en"],"license":"http://opendefinition.org/licenses/odc-odbl/","modified":"2016-08-04","programCode":["009:005"],"publisher":{"@type":"org:Organization","name":"Department of Health &amp; Human Services"},"title":"FDA Recognized Consensus Standards"}
