{"@type":"dcat:Dataset","accessLevel":"public","bureauCode":["009:38"],"contactPoint":{"fn":"admin","hasEmail":"mailto:HealthData@hhs.gov"},"description":"<p>This Nursing Home Quality Initiative (NHQI) website provides consumer and provider information regarding the quality of care in nursing homes. NHQI discusses quality measures that are shown at the Nursing Home Compare website (medicare.gov), which allows consumers, providers, States and researchers to compare information on nursing homes.</p>\n","identifier":"b7e5b3d7-f278-4cee-9b0f-38b1af82159e","keyword":["demonstrations","enrollment","hospital","inpatient","medicare","national","nursing-home","outcomes","providers","quality","quality-improvement-organization","reports","research","skilled-nursing-snf","survey","utilization"],"language":["en"],"license":"http://opendefinition.org/licenses/odc-odbl/","modified":"2016-04-05","publisher":{"@type":"org:Organization","name":"Department of Health &amp; Human Services"},"title":"Nursing Home Quality Initiative","programCode":["009:000"]}
