{"@type":"dcat:Dataset","accessLevel":"public","bureauCode":["009:20"],"contactPoint":{"fn":"CDCINFO","hasEmail":"mailto:cdcinfo@cdc.gov"},"description":"<p>Download the current cigarette use among adults slides. These slides are available in PDF and PowerPoint formats. The PDF version can be found at: <a href=\"https://chronicdata.cdc.gov/Survey-Data/Current-Cigarette-Use-Among-Adults-BRFSS-PDF-Slide/mea8-dy6j\">https://chronicdata.cdc.gov/Survey-Data/Current-Cigarette-Use-Among-Adul...</a></p>\n","distribution":[{"@type":"dcat:Distribution","downloadURL":"https://data.cdc.gov/download/nb96-p3q2/application/vnd.openxmlformats-officedocument.presentationml.presentation","mediaType":"application/unknown","format":"pptx","title":"pptx","identifier":"pptx-43b946fb-983a-4450-b628-f959e738fa47","interra-published":true}],"identifier":"https://data.cdc.gov/api/views/nb96-p3q2","keyword":["adult cigarette use","slides"],"language":["en"],"license":"http://opendefinition.org/licenses/odc-odbl/","modified":"2017-07-29","programCode":["009:020"],"publisher":{"@type":"org:Organization","name":"Centers for Disease Control and Prevention"},"title":"Current Cigarette Use Among Adults (BRFSS) PowerPoint Slides"}
